{
  "schemaVersion": 1,
  "targetLabelPolicy": "rule-backed-ner-v1",
  "targetLabels": [
    "PER",
    "ORG",
    "LOC"
  ],
  "allowNestedSpans": true,
  "allowOverlapDiagnostics": true,
  "comparators": [
    {
      "name": "spaCy",
      "runtime": "python",
      "version": "3.8.14",
      "model": "en_core_web_sm",
      "modelVersion": "3.8.0"
    },
    {
      "name": "compromise",
      "runtime": "javascript",
      "version": "14.15.0"
    }
  ],
  "notes": [
    "Frozen comparators are diagnostic baselines, not normative truth.",
    "The frozen comparator set is English-first; multilingual slices remain mandatory and may appear as not-run in comparator captures when a comparator is outside its declared language surface."
  ]
}
